{
    "metadata": {
        "title": "9780197653050 Print Impossible Project (2)",
        "author": "Unknown",
        "filename_pattern": "9780197653050_Print Impossible Project (2)"
    },
    "settings": {
        "toc_end_page": 9,
        "header_margin": 60,
        "footer_margin": 60,
        "footnote_size_thresh": 9.0
    },
    "chapters": [
        {
            "part": "Part 1",
            "num": "1",
            "title": "Introduction: How Ballet Histories Are Made\b"
        },
        {
            "part": "Part 1",
            "num": "2",
            "title": "1.\t The Shadow of Noverre: Ballet in a Narrative Perspective\b"
        },
        {
            "part": "Part 1",
            "num": "3",
            "title": "2.\t Modern Specters, or Body Politic to Body Balletic\b"
        },
        {
            "part": "Part 1",
            "num": "4",
            "title": "3.\t Ballet as a Verbal Art: Apostasy and Theodicy\b"
        },
        {
            "part": "Part 1",
            "num": "5",
            "title": "Epilogue\b"
        },
        {
            "part": "Part 1",
            "num": "6",
            "title": "Notes\b"
        },
        {
            "part": "Part 1",
            "num": "7",
            "title": "2.1.\t Maria Petipa in her \u201cLittle Peasant Man [ Muzhichok ]\u201d costume\b"
        },
        {
            "part": "Part 1",
            "num": "8",
            "title": "Administration, according to the Syllabus of Professor Skalkovsky\u201d\b"
        },
        {
            "part": "Part 1",
            "num": "9",
            "title": "2.3.\t Nicolas Lancret, La Camargo Dancing \b"
        },
        {
            "part": "Part 1",
            "num": "10",
            "title": "2.4.\t Olga Preobrajenska and Pavel Gerdt in The Trial of Damis \b"
        },
        {
            "part": "Part 1",
            "num": "11",
            "title": "2.5.\t Ivan Vsevolozhsky, \u201cKontrol\u2019naia kletka\u201d (The Comptroller\u2019s Cage)\b"
        },
        {
            "part": "Part 1",
            "num": "12",
            "title": "pedestal and Aleksandr Frolov worshiping her as a deity\b"
        },
        {
            "part": "Part 1",
            "num": "13",
            "title": "St. Anthony)\b"
        },
        {
            "part": "Part 1",
            "num": "14",
            "title": "production of The Sleeping Beauty \b"
        },
        {
            "part": "Part 1",
            "num": "15",
            "title": "(Sleeping Beauty\u2019s Nightstand)\b"
        },
        {
            "part": "Part 1",
            "num": "16",
            "title": "2.10.\t Ivan Vsevolozhsky, \u201cLes cloches de Corneville\u201d (The Bells of Corneville)\b"
        },
        {
            "part": "Part 1",
            "num": "17",
            "title": "2.11.\t \u201cEvil Genius of Russia\u201d\b"
        },
        {
            "part": "Part 1",
            "num": "18",
            "title": "3.1.\t Aleksandr Benois, \u201cBallerina,\u201d a costume design for Petrushka \b"
        },
        {
            "part": "Part 1",
            "num": "19",
            "title": "3.2.\t Tamara Karsavina as Ballerina in Petrushka \b"
        },
        {
            "part": "Part 1",
            "num": "20",
            "title": "3.3.\t Aleksandr Benois, \u201cThe First Street Dancer,\u201d a costume design for Petrushka \b"
        },
        {
            "part": "Part 1",
            "num": "21",
            "title": "for Petrushka \b"
        },
        {
            "part": "Part 1",
            "num": "23",
            "title": "3.6.\t Enrico Cechetti as Magician in Petrushka \b"
        },
        {
            "part": "Part 1",
            "num": "24",
            "title": "3.7.\t Enrico Cechetti in class with Anna Pavlova\b"
        },
        {
            "part": "Part 1",
            "num": "25",
            "title": "3.8.\t L\u00e9on Bakst, \u201cThe French Doll,\u201d a costume design for The Fairy Doll \b"
        },
        {
            "part": "Part 1",
            "num": "26",
            "title": "3.9.\t L\u00e9on Bakst, \u201cThe Postman,\u201d a costume design for The Fairy Doll \b"
        },
        {
            "part": "Part 1",
            "num": "27",
            "title": "3.10.\t L\u00e9on Bakst, \u201cThe Officer\u2019s Servant,\u201d a costume design for The Fairy Doll \b"
        },
        {
            "part": "Part 1",
            "num": "28",
            "title": "3.11.\t L\u00e9on Bakst, set design for the first scene of The Fairy Doll \b"
        },
        {
            "part": "Part 1",
            "num": "29",
            "title": "3.12.\t Aleksandr Benois, set design for Petrushka \b"
        }
    ]
}